<?xml version="1.0" encoding="UTF-8"?>
<!DOCTYPE suite SYSTEM "https://testng.org/testng-1.0.dtd">
<suite parallel="false" name="Orange HRM Automation Suite">

    <listeners>
        <listener class-name="com.orangehrm.listeners.CustomListeners"/>
    </listeners>

    <test name="Regression Suite">
        <classes>
            <class name="com.orangehrm.testcases.OrangeHRMLoginTest"/>
            <class name="com.orangehrm.testcases.OrangeHRMPIMTest"/>
            <class name="com.orangehrm.testcases.OrangeHRMPersonalDetailsTest"/>
            <class name="com.orangehrm.testcases.OrangeHRMQualificationTest"/>
            <class name="com.orangehrm.testcases.OrangeHRMLogOutTest"/>
            <class name="com.orangehrm.testcases.OrangeHRMForgotPasswordTest"/>
        </classes>
    </test> <!-- testng.xml -->

</suite> <!-- Suite -->

